pyvyu/__init__.py
pyvyu/cell/Cell.py
pyvyu/cell/__init__.py
pyvyu/column/Column.py
pyvyu/column/__init__.py
pyvyu/pyvyu.py
pyvyu/spreadsheet/Spreadsheet.py
pyvyu/spreadsheet/__init__.py
pyvyu-0.3.6.dist-info/LICENSE
pyvyu-0.3.6.dist-info/WHEEL
pyvyu-0.3.6.dist-info/METADATA
pyvyu-0.3.6.dist-info/RECORD
